<?xml version="1.0" encoding="utf-8"?>
<ModsConfigData>
  <version>1.1.2654 rev674</version>
  <activeMods>
    <li>brrainz.harmony</li>
    <li>ludeon.rimworld</li>
    <li>ludeon.rimworld.royalty</li>
    <li>rwmt.multiplayer</li>
    <li>rwmt.multiplayercompatibility</li>
    <li>unlimitedhugs.hugslib</li>
    <li>erdelf.humanoidalienraces</li>
    <li>dninemfive.qualitycooldown</li>
    <li>dubwise.dubsperformanceanalyzer</li>
    <li>erdelf.minifyeverything</li>
    <li>frozensnowfox.filthvanisheswithrainandtime</li>
    <li>hobtook.mortaraccuracy</li>
    <li>jaxe.foodrestrictions</li>
    <li>moretraitslots.kv.rw</li>
    <li>neceros.badcanbegood</li>
    <li>neceros.roomsizetolerance</li>
    <li>notfood.frameratecontrol</li>
    <li>ogre.ogrestack</li>
    <li>owlchemist.bettervanillamasking</li>
    <li>owlchemist.optimizationmeats</li>
    <li>shotgunfrenzy.prioritytreatment</li>
    <li>showhair.kv.rw</li>
    <li>smashphil.carrycapacityfixed</li>
    <li>syrchalis.harvestyieldpatch</li>
    <li>xeonovadan.propershotguns</li>
    <li>aelanna.eccentricextras.angelhairs</li>
    <li>aelanna.eccentrictech.cosmetics</li>
    <li>ameiro.animehairs</li>
    <li>cp.chicken.mitchell.hairstyles</li>
    <li>edge.varietyhair</li>
    <li>gloomy.gloomyfacemk2</li>
    <li>gloomy.gloomyhairmk2</li>
    <li>jintuzilamian.hairstyle.afumenshairstyles</li>
    <li>jintuzilamian.hairstyle.afuwomenshairstyles</li>
    <li>lingluo.lovelyhairstyle</li>
    <li>mlie.ponytailiskawaii</li>
    <li>rimsenal.hair</li>
    <li>sakama.roppoihair</li>
    <li>spoonshortage.spoonshairmod</li>
    <li>uru.keomono.friends.hair</li>
    <li>vanya.agent.lolidrophairshop</li>
    <li>won.hair</li>
    <li>won2.hair</li>
    <li>handandfootwear.kv.rw</li>
    <li>mlie.mercerbackpacks</li>
    <li>shinzy.apparello</li>
    <li>spoonshortage.fashionrimsta</li>
    <li>janson.weapontech11</li>
    <li>yoseisan.rimcolle</li>
    <li>alex.birdup.cockatiel</li>
    <li>daniledman.cyberfauna</li>
    <li>drzhivago.vanillaanimalsoverhaulreloaded</li>
    <li>sarg.alphaanimals</li>
    <li>spincrus.dinosauria</li>
    <li>frozensnowfox.vanillabionicsexpansion</li>
    <li>automatic.bionicicons</li>
    <li>com.prostheticnomissingbodyparts.rimworld.mod</li>
    <li>darthsergeant.nursejob</li>
    <li>linq.deathrattle</li>
    <li>mlie.xndadrenaline</li>
    <li>pelador.commonailments</li>
    <li>pelador.drugpolicyfix</li>
    <li>pelador.drugresponse</li>
    <li>pelador.medicalsupplements</li>
    <li>proxyer.desurgeries.desurgeries</li>
    <li>syrchalis.prosthetictable</li>
    <li>dubwise.dubspaintshop</li>
    <li>elif.flooringanddecorativeoptions</li>
    <li>fantasyfan.decorativecliffs</li>
    <li>fluffy.stuffedfloors</li>
    <li>lat.veedeco</li>
    <li>mlie.sdchickennest</li>
    <li>neceros.ceilinglightsvanillaedition</li>
    <li>nif.vanillafencestab</li>
    <li>pyrce.mass.graves</li>
    <li>radzerp.wallcorners</li>
    <li>ruyan.doors</li>
    <li>telkir.tmods.morefloors</li>
    <li>syrchalis.universalfermenter</li>
    <li>crustypeanut.rc2.core</li>
    <li>dismarzero.vgp.vgpgardendrinksuf</li>
    <li>jamaicancastle.rf.fertilefields</li>
    <li>notfood.seedsplease</li>
    <li>shadow.spaiomegapatch</li>
    <li>saucypigeon.wildcultivation</li>
    <li>vanillaexpanded.vcooke</li>
    <li>4loris4.morelinkables</li>
    <li>5katz.commschat</li>
    <li>babies.and.children</li>
    <li>boe.psychocasts</li>
    <li>cucumpear.storage</li>
    <li>dubwise.dubsbadhygiene</li>
    <li>dubwise.dubsrimkit</li>
    <li>dubwise.rimefeller</li>
    <li>kikohi.tamingartifact</li>
    <li>n7huntsman.ceramics</li>
    <li>notfood.mendandrecycle</li>
    <li>pelador.fireextinguisher</li>
    <li>proxyer.desurgeries.dbhpatch</li>
    <li>rimfridge.kv.rw</li>
    <li>syrchalis.doormats</li>
    <li>tachyonite.pawnmorpherpublic</li>
    <li>vanillaexpanded.vcef</li>
    <li>solaris.furniturebase</li>
    <li>dalrae.gloomydeco</li>
    <li>semo583.gloomyhextrahuhkitchen</li>
    <li>tikubonn.stuffeddoll</li>
    <li>zymex.gloomyvanillaoverhaul</li>
    <li>merthsoft.timeofdayswitches</li>
    <li>supes.powerlogic.core</li>
    <li>bob.draggablecornerss</li>
    <li>dninemfive.d9framework</li>
    <li>navyseal5.moreharvestdesignators</li>
    <li>pelador.bestmix</li>
    <li>tammybee.cutplantsbeforebuilding</li>
    <li>thewirelord354.conduitdeconstruct</li>
    <li>earthyturtle.letstrade</li>
    <li>ghxx.techadvancing</li>
    <li>katavrik.crashlanding</li>
    <li>nitrodev.inspiration</li>
    <li>notfood.infused</li>
    <li>vanillaexpanded.vee</li>
    <li>oblitus.mylittleplanet</li>
    <li>syrchalis.setupcamp</li>
    <li>222821750.realdining</li>
    <li>avilmask.commonsense</li>
    <li>bar0th.norandomrelations</li>
    <li>codeoptimist.jobsofopportunity</li>
    <li>consolidatedtraits.kv.rw</li>
    <li>dninemfive.pepinyourstep</li>
    <li>gguake.ai.dsfi</li>
    <li>jamaicancastle.shoo</li>
    <li>mehni.pickupandhaul</li>
    <li>petetimessix.simplesidearms</li>
    <li>netrve.usemelee</li>
    <li>notfood.morethancapable</li>
    <li>oblitus.animalslogic</li>
    <li>pathavoid.kv.rw</li>
    <li>pelador.firewarden</li>
    <li>relaxedotter.moreinspirationtypes</li>
    <li>revolus.animalsarefun</li>
    <li>tradingspot.kv.rw</li>
    <li>automatic.autolinks</li>
    <li>automatic.recipeicons</li>
    <li>bob.tickspersecond</li>
    <li>brrainz.cameraplus</li>
    <li>com.bymarcin.architecticons</li>
    <li>compilatron.powertab</li>
    <li>diddily.poweralerts</li>
    <li>dingo.deeporeidentifier</li>
    <li>dubwise.dubsmintmenus</li>
    <li>dubwise.dubsmintminimap</li>
    <li>gguake.ui.armorinfo</li>
    <li>gguake.ui.simplesearchbar</li>
    <li>mehni.numbers</li>
    <li>neptimus7.progressrenderer</li>
    <li>notfood.outfitted</li>
    <li>notfood.researchpal</li>
    <li>notfood.yasp</li>
    <li>raven.colorcodedtraits</li>
    <li>revolus.textilestats</li>
    <li>tammybee.restocknotification</li>
    <li>caesarv6.damageindicators</li>
    <li>jaxe.bubbles</li>
    <li>fluffy.modmanager</li>
    <li>notfood.glue</li>
  </activeMods>
  <knownExpansions>
    <li>ludeon.rimworld.royalty</li>
  </knownExpansions>
</ModsConfigData>